bda.plone.cart-2.0b1-py3.9-nspkg.pth
bda/plone/cart/__init__.py
bda/plone/cart/cart.py
bda/plone/cart/cartitem.py
bda/plone/cart/configure.zcml
bda/plone/cart/cookie.py
bda/plone/cart/i18n.sh
bda/plone/cart/interfaces.py
bda/plone/cart/profiles.zcml
bda/plone/cart/setuphandlers.py
bda/plone/cart/shipping.py
bda/plone/cart/utils.py
bda/plone/cart/browser/__init__.py
bda/plone/cart/browser/configure.zcml
bda/plone/cart/browser/portlet.pt
bda/plone/cart/browser/portlet.py
bda/plone/cart/browser/summary.pt
bda/plone/cart/browser/tile.pt
bda/plone/cart/browser/view.pt
bda/plone/cart/browser/viewlet.pt
bda/plone/cart/browser/images/arrow_refresh.png
bda/plone/cart/browser/images/cart_delete.png
bda/plone/cart/browser/images/cart_go.png
bda/plone/cart/browser/images/cart_put.png
bda/plone/cart/browser/images/cart_refresh.png
bda/plone/cart/browser/images/delete.png
bda/plone/cart/browser/images/delete2.png
bda/plone/cart/browser/images/xdelete.png
bda/plone/cart/browser/static/cart.css
bda/plone/cart/browser/static/cart.css.map
bda/plone/cart/browser/static/cart.js
bda/plone/cart/browser/static/cart.min.css
bda/plone/cart/browser/static/cart.min.css.map
bda/plone/cart/browser/static/cookie.functions.js
bda/plone/cart/locales/bda.plone.cart.pot
bda/plone/cart/locales/manual.pot
bda/plone/cart/locales/de/LC_MESSAGES/bda.plone.cart.po
bda/plone/cart/locales/en/LC_MESSAGES/bda.plone.cart.po
bda/plone/cart/locales/fr/LC_MESSAGES/bda.plone.cart.po
bda/plone/cart/locales/it/LC_MESSAGES/bda.plone.cart.po
bda/plone/cart/locales/nl/LC_MESSAGES/bda.plone.cart.po
bda/plone/cart/locales/nn/LC_MESSAGES/bda.plone.cart.po
bda/plone/cart/locales/no/LC_MESSAGES/bda.plone.cart.po
bda/plone/cart/profiles/default/browserlayer.xml
bda/plone/cart/profiles/default/metadata.xml
bda/plone/cart/profiles/default/portlets.xml
bda/plone/cart/profiles/default/registry.xml
bda/plone/cart/profiles/default/viewlets.xml
bda/plone/cart/profiles/uninstall/browserlayer.xml
bda.plone.cart-2.0b1.dist-info/LICENSE.rst
bda.plone.cart-2.0b1.dist-info/LICENSE_GPL.rst
bda.plone.cart-2.0b1.dist-info/METADATA
bda.plone.cart-2.0b1.dist-info/WHEEL
bda.plone.cart-2.0b1.dist-info/namespace_packages.txt
bda.plone.cart-2.0b1.dist-info/top_level.txt
bda.plone.cart-2.0b1.dist-info/RECORD
